SajadEnc/SajadEnc.py
SajadEnc/__init__.py
SajadBase-2.1.dist-info/METADATA
SajadBase-2.1.dist-info/WHEEL
SajadBase-2.1.dist-info/top_level.txt
SajadBase-2.1.dist-info/RECORD
