Metadata-Version: 2.1
Name: SajadBase
Version: 2.1
Summary: an encryption library for @K_D_QQ sajad
Author: SajadBase
Classifier: Programming Language :: Python :: 3
